iluxaMod/__init__.py
iluxaMod/arduino.py
iluxaMod/automation.py
iluxaMod/barcode.py
iluxaMod/convertors.py
iluxaMod/distance.py
iluxaMod/keygen.py
iluxaMod/mechanics.py
iluxaMod/pickle.py
iluxaMod/postgreSQL.py
iluxaMod/qr.py
iluxaMod/termux.py
iluxaMod/tgbot.py
iluxaMod/tools.py
iluxaMod-3.0.2.dist-info/METADATA
iluxaMod-3.0.2.dist-info/WHEEL
iluxaMod-3.0.2.dist-info/top_level.txt
iluxaMod-3.0.2.dist-info/RECORD
